src/__init__.py
src/cmdline.py
src/common/__init__.py
src/common/ignore_warnings.py
src/common/utils.py
src/config/__init__.py
src/config/config.py
src/downloader/__init__.py
src/downloader/download.py
src/downloader/gh_api.py
src/downloader/utils.py
src/indexer/__init__.py
src/indexer/index.py
src/logger/__init__.py
src/logger/log.py
src/queries/__init__.py
src/reporter/__init__.py
src/reporter/report.py
src/reporter/slack_reporter.py
src/storage/__init__.py
src/storage/neo4j_graph.py
src/storage/neo4j_utils.py
src/storage/redis_connection.py
src/storage/redis_utils.py
src/workflow_components/__init__.py
src/workflow_components/composite_action.py
src/workflow_components/dependency.py
src/workflow_components/parsing_utils.py
src/workflow_components/workflow.py
raven_cycode-1.0.9.dist-info/LICENSE.md
raven_cycode-1.0.9.dist-info/METADATA
raven_cycode-1.0.9.dist-info/WHEEL
raven_cycode-1.0.9.dist-info/entry_points.txt
raven_cycode-1.0.9.dist-info/top_level.txt
raven_cycode-1.0.9.dist-info/RECORD
