Metadata-Version: 2.1
Name: raven-cycode
Version: 1.0.9
Summary: RAVEN (Risk Analysis and Vulnerability Enumeration for CI/CD)
Home-page: https://github.com/CycodeLabs/raven
Author: ['Cycode <research@cycode.com>']
License: Apache License 2.0
Project-URL: Source, https://github.com/CycodeLabs/raven
Keywords: cycode,raven,security,ci/cd
Classifier: Programming Language :: Python :: 3
Classifier: Programming Language :: Python :: 3.9
Classifier: Programming Language :: Python :: 3.10
Classifier: Programming Language :: Python :: 3.11
Classifier: Programming Language :: Python :: 3.12
Classifier: Programming Language :: Python :: 3 :: Only
Classifier: Operating System :: Unix
Classifier: Operating System :: MacOS
Classifier: Intended Audience :: Science/Research
Classifier: Topic :: Security
Requires-Python: >=3.9
License-File: LICENSE.md
Requires-Dist: certifi ==2024.2.2
Requires-Dist: charset-normalizer ==3.3.2
Requires-Dist: colorama ==0.4.6
Requires-Dist: idna ==3.7
Requires-Dist: iniconfig ==2.0.0
Requires-Dist: interchange ==2021.0.4
Requires-Dist: loguru ==0.7.2
Requires-Dist: monotonic ==1.6
Requires-Dist: packaging ==24.0
Requires-Dist: pansi ==2020.7.3
Requires-Dist: pluggy ==1.4.0
Requires-Dist: py2neo ==2021.2.4
Requires-Dist: Pygments ==2.17.2
Requires-Dist: pytest ==8.1.1
Requires-Dist: pytz ==2023.3.post1
Requires-Dist: PyYAML ==6.0.1
Requires-Dist: redis ==5.0.3
Requires-Dist: requests ==2.31.0
Requires-Dist: six ==1.16.0
Requires-Dist: slack-sdk ==3.27.1
Requires-Dist: tqdm ==4.66.2
Requires-Dist: urllib3 ==2.2.1
